mongoutils/__init__.py
mongoutils/mongoutils.py
boost_art_mongoutils-0.1.6.dist-info/METADATA
boost_art_mongoutils-0.1.6.dist-info/WHEEL
boost_art_mongoutils-0.1.6.dist-info/top_level.txt
boost_art_mongoutils-0.1.6.dist-info/RECORD
